aifile/__init__.py
aifile/file_manager.py
aifile-0.5.dist-info/METADATA
aifile-0.5.dist-info/WHEEL
aifile-0.5.dist-info/entry_points.txt
aifile-0.5.dist-info/top_level.txt
aifile-0.5.dist-info/RECORD
