Metadata-Version: 2.1
Name: aifile
Version: 0.5
Requires-Dist: scikit-learn
Requires-Dist: numpy
Requires-Dist: speechrecognition
